climate_ref_core/__init__.py
climate_ref_core/constraints.py
climate_ref_core/dataset_registry.py
climate_ref_core/datasets.py
climate_ref_core/diagnostics.py
climate_ref_core/env.py
climate_ref_core/exceptions.py
climate_ref_core/executor.py
climate_ref_core/logging.py
climate_ref_core/providers.py
climate_ref_core/py.typed
climate_ref_core/metric_values/__init__.py
climate_ref_core/metric_values/typing.py
climate_ref_core/pycmec/README.md
climate_ref_core/pycmec/__init__.py
climate_ref_core/pycmec/controlled_vocabulary.py
climate_ref_core/pycmec/cv_cmip7_aft.yaml
climate_ref_core/pycmec/metric.py
climate_ref_core/pycmec/output.py
climate_ref_core-0.8.1.dist-info/METADATA
climate_ref_core-0.8.1.dist-info/WHEEL
climate_ref_core-0.8.1.dist-info/licenses/LICENCE
climate_ref_core-0.8.1.dist-info/licenses/NOTICE
climate_ref_core-0.8.1.dist-info/RECORD
