Metadata-Version: 2.4
Name: climate-ref-core
Version: 0.8.1
Summary: Core library for the CMIP Rapid Evaluation Framework
Author-email: Jared Lewis <jared.lewis@climate-resource.com>, Mika Pflueger <mika.pflueger@climate-resource.com>, Bouwe Andela <b.andela@esciencecenter.nl>, Jiwoo Lee <lee1043@llnl.gov>, Min Xu <xum1@ornl.gov>, Nathan Collier <collierno@ornl.gov>, Dora Hegedus <dora.hegedus@stfc.ac.uk>
License-Expression: Apache-2.0
License-File: LICENCE
License-File: NOTICE
Classifier: Development Status :: 3 - Alpha
Classifier: Intended Audience :: Developers
Classifier: Intended Audience :: Science/Research
Classifier: License :: OSI Approved :: Apache Software License
Classifier: Operating System :: OS Independent
Classifier: Programming Language :: Python
Classifier: Programming Language :: Python :: 3
Classifier: Programming Language :: Python :: 3.11
Classifier: Programming Language :: Python :: 3.12
Classifier: Programming Language :: Python :: 3.13
Classifier: Topic :: Scientific/Engineering
Requires-Python: >=3.11
Requires-Dist: attrs>=23.2.0
Requires-Dist: cattrs>=24.1
Requires-Dist: environs>=11
Requires-Dist: fastprogress==1.0.5
Requires-Dist: loguru>=0.7.0
Requires-Dist: numpy>=2.0.0
Requires-Dist: pandas>=2.1.0
Requires-Dist: pooch<2,>=1.8.0
Requires-Dist: pydantic>=2.10.6
Requires-Dist: pyyaml>=6.0.2
Requires-Dist: requests
Requires-Dist: rich
Requires-Dist: setuptools<81
Requires-Dist: typing-extensions
